google_client/__init__.py
google_client/drive.py
google_client/gmail.py
google_client/service.py
google_client_helper-0.0.4.dist-info/licenses/LICENSE
google_client_helper-0.0.4.dist-info/METADATA
google_client_helper-0.0.4.dist-info/WHEEL
google_client_helper-0.0.4.dist-info/RECORD
