Metadata-Version: 2.4
Name: google-client-helper
Version: 0.0.4
Summary: Helpers for the Google Drive and Gmail APIs using a service account
License: MIT
License-File: LICENSE
Author: Ian Jones
Author-email: you@example.com
Requires-Python: >=3.9
Classifier: License :: OSI Approved :: MIT License
Classifier: Programming Language :: Python :: 3
Classifier: Programming Language :: Python :: 3.9
Classifier: Programming Language :: Python :: 3.10
Classifier: Programming Language :: Python :: 3.11
Classifier: Programming Language :: Python :: 3.12
Classifier: Programming Language :: Python :: 3.13
Classifier: Programming Language :: Python :: 3.14
Requires-Dist: google-api-python-client (>=2.187.0,<3.0.0)
Requires-Dist: google-auth (>=2.43.0,<3.0.0)
Project-URL: Homepage, https://github.com/jonesim/google-client-helper
